test_case_elf/__init__.py
test_case_elf/field.py
test_case_elf/pipe.py
TestCaseElf-0.0.1.dist-info/LICENSE
TestCaseElf-0.0.1.dist-info/METADATA
TestCaseElf-0.0.1.dist-info/WHEEL
TestCaseElf-0.0.1.dist-info/top_level.txt
TestCaseElf-0.0.1.dist-info/RECORD
