Metadata-Version: 2.1
Name: TestCaseElf
Version: 0.0.1
Summary: Tese cases generating helper tool.
Home-page: https://github.com/panoslin/TestCaseElf
Author: Panos Lin
Author-email: lghpanos@gmail.com
License: MIT
Project-URL: Bug Tracker, https://github.com/panoslin/TestCaseElf/issues
Keywords: test,testing,test case,unit test,test case generat
Platform: UNKNOWN
Classifier: Programming Language :: Python :: 3
Classifier: License :: OSI Approved :: MIT License
Classifier: Operating System :: OS Independent
Requires-Python: >=3.8
License-File: LICENSE
Requires-Dist: pandas (==1.3.5)
